{
  "respuestaCuil": {
    "cuil": "20957314422"
  },

  "respuestaEstadoCivil": [
    {
      "value": "1",
      "label": "Soltero/a"
    },
    {
      "value": "2",
      "label": "Casado/a"
    },
    {
      "value": "3",
      "label": "Separado/a"
    },
    {
      "value": "4",
      "label": "Divorciado/a"
    },
    {
      "value": "5",
      "label": "Viudo/a"
    },
    {
      "value": "6",
      "label": "Unión Convivencial Registrada"
    },
    {
      "value": "7",
      "label": "Unión Convivencial No Registrada"
    }
  ],
  "respuestaPaises": [
    {
      "id": 58,
      "descripcion": "ARGENTINA",
      "codigo": "80"
    },
    {
      "id": 181,
      "descripcion": "ARMENIA",
      "codigo": "50"
    },
    {
      "id": 68,
      "descripcion": "ARUBA",
      "codigo": "92"
    },
    {
      "id": 182,
      "descripcion": "ARUBA",
      "codigo": "52"
    },
    {
      "id": 69,
      "descripcion": "ASCENCION",
      "codigo": "93"
    },
    {
      "id": 239,
      "descripcion": "ASCENCION",
      "codigo": "236"
    },
    {
      "id": 20,
      "descripcion": "AUSTRALIA",
      "codigo": "21"
    },
    {
      "id": 13,
      "descripcion": "AUSTRIA",
      "codigo": "13"
    },
    {
      "id": 183,
      "descripcion": "AZERBAIDZHA",
      "codigo": "59"
    },
    {
      "id": 184,
      "descripcion": "BAHAMAS",
      "codigo": "60"
    }
  ],
  "respuestaFechaNacimiento": {
    "isValid": true
  },
  "respuestaLocalidades": [
    {
      "localityModel": [
        {
          "id": 336,
          "descripcion": "CAPITAL FEDERAL",
          "codigo": "1426",
          "cp": "1426",
          "idProvincia": 1
        }
      ],
      "sucursalModel": []
    },
    {
      "localityModel": [
        {
          "id": 597,
          "descripcion": "DIAZ",
          "codigo": "2222",
          "cp": "2222",
          "idProvincia": 21
        }
      ],
      "sucursalModel": []
    },
    {
      "localityModel": [
        {
          "id": 1225,
          "descripcion": "ANCA",
          "codigo": "4321",
          "cp": "4321",
          "idProvincia": 22
        }
      ],
      "sucursalModel": []
    },
    {
      "localityModel": [
        {
          "id": 1253,
          "descripcion": "SAN PEDRO DE JUJUY",
          "codigo": "4500",
          "cp": "4500",
          "idProvincia": 10
        }
      ],
      "sucursalModel": []
    }
  ]
}
